pypirun/__init__.py
pypirun/__main__.py
pypirun/arguments.py
pypirun/cli.py
pypirun/utility.py
pypirun-3.0.966010.dist-info/LICENSE
pypirun-3.0.966010.dist-info/METADATA
pypirun-3.0.966010.dist-info/WHEEL
pypirun-3.0.966010.dist-info/entry_points.txt
pypirun-3.0.966010.dist-info/top_level.txt
pypirun-3.0.966010.dist-info/zip-safe
pypirun-3.0.966010.dist-info/RECORD
