Metadata-Version: 2.1
Name: pypirun
Version: 3.0.966010
Summary: Command line utility to run a command, installing needed python packages if it is not installed
Home-page: https://github.com/yahoo/pypirun
Author: Verizon Media Python Platform Team
Author-email: 254983+dwighthubbard@users.noreply.github.com
License: BSD License
Keywords: python virtualenv pypi cli
Classifier: Development Status :: 5 - Production/Stable
Classifier: Intended Audience :: Developers
Classifier: License :: OSI Approved :: BSD License
Classifier: Programming Language :: Python :: 3 :: Only
Classifier: Programming Language :: Python :: 3.8
Classifier: Programming Language :: Python :: 3.9
Classifier: Programming Language :: Python :: 3.10
Classifier: Programming Language :: Python :: 3.11
Requires-Python: >=3.9
License-File: LICENSE
